fiberlib/__init__.py
fiberlib/module.py
fiberlib-0.0.3.dist-info/LICENSE
fiberlib-0.0.3.dist-info/METADATA
fiberlib-0.0.3.dist-info/WHEEL
fiberlib-0.0.3.dist-info/top_level.txt
fiberlib-0.0.3.dist-info/RECORD
