Metadata-Version: 2.1
Name: fiberlib
Version: 0.0.3
Summary: Package for Elastic Optical Networking
Home-page: UNKNOWN
Author: Mostafa Ayaz
Author-email: m.ayaz@email.kntu.ac.ir
License: UNKNOWN
Platform: UNKNOWN
Requires-Python: >=3.6
License-File: LICENSE
